ls_api_clients/__init__.py
ls_api_clients/ls_api_client.py
ls_api_clients-0.30.0.dist-info/licenses/LICENSE
ls_api_clients-0.30.0.dist-info/METADATA
ls_api_clients-0.30.0.dist-info/WHEEL
ls_api_clients-0.30.0.dist-info/top_level.txt
ls_api_clients-0.30.0.dist-info/RECORD
